nonebot_plugin_bard/__init__.py
nonebot_plugin_bard/config.py
nonebot_plugin_bard/gemini_webapi/__init__.py
nonebot_plugin_bard/gemini_webapi/client.py
nonebot_plugin_bard/gemini_webapi/constant.py
nonebot_plugin_bard/gemini_webapi/exceptions.py
nonebot_plugin_bard/gemini_webapi/types/__init__.py
nonebot_plugin_bard/gemini_webapi/types/candidate.py
nonebot_plugin_bard/gemini_webapi/types/image.py
nonebot_plugin_bard/gemini_webapi/types/modeloutput.py
nonebot_plugin_bard/gemini_webapi/utils.py
nonebot_plugin_bard/images/demo1.jpg
nonebot_plugin_bard/images/demo2.jpg
nonebot_plugin_bard/images/demo3.jpg
nonebot_plugin_bard-0.5.1.dist-info/METADATA
nonebot_plugin_bard-0.5.1.dist-info/WHEEL
nonebot_plugin_bard-0.5.1.dist-info/RECORD
