Metadata-Version: 2.1
Name: nonebot-plugin-bard
Version: 0.5.1
Summary: A nonebot plugin for Bard
License: MIT
Author: Alpaca
Author-email: alpaca@bupt.edu.cn
Requires-Python: >=3.10,<4.0
Classifier: License :: OSI Approved :: MIT License
Classifier: Programming Language :: Python :: 3
Classifier: Programming Language :: Python :: 3.10
Classifier: Programming Language :: Python :: 3.11
Classifier: Programming Language :: Python :: 3.12
Requires-Dist: nonebot-adapter-onebot (>=2.2.1,<3.0.0)
Requires-Dist: nonebot2 (>=2.0.0rc3,<3.0.0)
Requires-Dist: websocket-client (>=1.6.1,<2.0.0)
